lbry_batch_uploader/__init__.py
lbry_batch_uploader/__main__.py
lbry_batch_uploader/parser.py
lbry_batch_uploader/py.typed
lbry_batch_uploader/uploader.py
lbry_batch_uploader/utils.py
lbry_batch_uploader-1.1.0.dist-info/LICENSE
lbry_batch_uploader-1.1.0.dist-info/METADATA
lbry_batch_uploader-1.1.0.dist-info/WHEEL
lbry_batch_uploader-1.1.0.dist-info/top_level.txt
lbry_batch_uploader-1.1.0.dist-info/RECORD
