Metadata-Version: 2.1
Name: lbry-batch-uploader
Version: 1.1.0
Summary: A convenient batch uploader for LBRY Desktop written in Python
Home-page: https://github.com/thk-cheng/lbry_batch_uploader
Author: thk-cheng
Author-email: kenneth.cheng.tsun.him@gmail.com
License: MIT
Project-URL: Bug Tracker, https://github.com/thk-cheng/lbry_batch_uploader/issues
Platform: linux
Platform: osx
Platform: unix
Classifier: Programming Language :: Python :: 3
Classifier: Programming Language :: Python :: 3 :: Only
Classifier: Programming Language :: Python :: 3.8
Classifier: Programming Language :: Python :: 3.9
Classifier: Programming Language :: Python :: 3.10
Requires-Python: >=3.8
License-File: LICENSE
Requires-Dist: requests (>=2)
Provides-Extra: testing
Requires-Dist: black (>=22.0.0) ; extra == 'testing'
Requires-Dist: flake8 (>=4.0.0) ; extra == 'testing'
Requires-Dist: mypy (>=0.950) ; extra == 'testing'
Requires-Dist: pre-commit (>=2.19.0) ; extra == 'testing'
Requires-Dist: pytest (>=7.0.0) ; extra == 'testing'
Requires-Dist: pytest-cov (>=3.0.0) ; extra == 'testing'
Requires-Dist: tox (>=3.25.0) ; extra == 'testing'
Requires-Dist: types-requests (>=2.27.0) ; extra == 'testing'
